d22d/__init__.py
d22d/task.py
d22d/version.py
d22d/model/__init__.py
d22d/model/diskcachemodel.py
d22d/model/filemodel.py
d22d/model/filetypemodel.py
d22d/model/ftpmodel.py
d22d/model/ftpserver.py
d22d/model/midhardware.py
d22d/model/mysqlmodel.py
d22d/model/mysqlpool.py
d22d/model/redismodel.py
d22d/model/sftpmodel.py
d22d/model/supervisormodel.py
d22d/model/zipmodel.py
d22d/pipline/__init__.py
d22d/utils/__init__.py
d22d/utils/decorators.py
d22d/utils/diskcacheofsqlite.py
d22d/utils/drive_detect.py
d22d/utils/exceptions.py
d22d/utils/f2r.py
d22d/utils/fetch_to_requests.py
d22d/utils/ftpup.py
d22d/utils/install_dependencies.py
d22d/utils/logger.py
d22d/utils/logging.conf
d22d/utils/logutils.py
d22d/utils/pickleutils.py
d22d/utils/rarutils.py
d22d/utils/req_conflit.py
d22d/utils/rsa.py
d22d/utils/timeutils.py
d22d/utils/utils.py
d22d/utils/ziputils.py
d22d/utils/db/__init__.py
d22d/utils/db/myutils.py
d22d/utils/db/sqlfileextra.py
d22d-1.1.80.dist-info/LICENSE
d22d-1.1.80.dist-info/METADATA
d22d-1.1.80.dist-info/WHEEL
d22d-1.1.80.dist-info/top_level.txt
d22d-1.1.80.dist-info/zip-safe
d22d-1.1.80.dist-info/RECORD
