Metadata-Version: 2.1
Name: d22d
Version: 1.1.80
Summary: Migrating form DataBase to DataBase by 2 lines code
Home-page: https://github.com/DJMIN/D2D
Author: readerror
Author-email: readerror@sina.com
Maintainer: readerror
Maintainer-email: readerror@sina.com
License: GPL License
Platform: all
Requires-Python: >=3.6
License-File: LICENSE
Requires-Dist: wheel
Requires-Dist: python-logstash
Requires-Dist: gunicorn
Requires-Dist: kafka-python
Requires-Dist: chardet
Requires-Dist: baostock
Requires-Dist: async-timeout
Requires-Dist: thrift
Requires-Dist: pyquery
Requires-Dist: dnspython
Requires-Dist: Flask-Migrate
Requires-Dist: coverage
Requires-Dist: bs4
Requires-Dist: itsdangerous
Requires-Dist: pysocks
Requires-Dist: Werkzeug
Requires-Dist: pathlib2
Requires-Dist: nose
Requires-Dist: zipp
Requires-Dist: pymongo
Requires-Dist: psycopg2-binary
Requires-Dist: logstash-formatter
Requires-Dist: PyMySQL
Requires-Dist: urllib3
Requires-Dist: python-logstash-async
Requires-Dist: gevent
Requires-Dist: xlsxwriter
Requires-Dist: mongoengine
Requires-Dist: phone
Requires-Dist: click
Requires-Dist: rednose
Requires-Dist: eventlet
Requires-Dist: func-timeout
Requires-Dist: simplejson
Requires-Dist: PyHive
Requires-Dist: msgpack
Requires-Dist: concurrent-log-handler
Requires-Dist: watchdog
Requires-Dist: docker
Requires-Dist: requests[socks]
Requires-Dist: openpyxl
Requires-Dist: pymysql
Requires-Dist: flask
Requires-Dist: lxml
Requires-Dist: pandas
Requires-Dist: python-dateutil
Requires-Dist: pytest
Requires-Dist: numpy
Requires-Dist: SQLAlchemy
Requires-Dist: rarfile
Requires-Dist: bcrypt
Requires-Dist: greenlet
Requires-Dist: xlrd
Requires-Dist: demjson3
Requires-Dist: tushare
Requires-Dist: psutil
Requires-Dist: arrow
Requires-Dist: tornado
Requires-Dist: setuptools
Requires-Dist: pycryptodome
Requires-Dist: wrapt
Requires-Dist: twine
Requires-Dist: sqlparse
Requires-Dist: six
Requires-Dist: orjson
Requires-Dist: requests (>=2.27.1)
Requires-Dist: elasticsearch-dsl (>=6.1)
Requires-Dist: PyMySQL (>=0.9.3)
Requires-Dist: mysql-connector-python (>=8.0.27)
Requires-Dist: redis (>=3.2.1)
Requires-Dist: DBUtils (>=2.0)
Requires-Dist: elasticsearch (>=6.1.1)
Requires-Dist: diskcache
Requires-Dist: tomorrow3
Requires-Dist: clickhouse-driver
Requires-Dist: zip-files
Requires-Dist: paramiko
Requires-Dist: python-magic
Requires-Dist: pyftpdlib
Requires-Dist: pysnooper
Requires-Dist: walrus
Requires-Dist: universal-object-pool
Requires-Dist: requests-ftp
Requires-Dist: webdriver-manager
Requires-Dist: auto-run-on-remote
Requires-Dist: pika (>=1.2.0)
Requires-Dist: aiohttp
Requires-Dist: PySnooper (>=1.0.0)
Requires-Dist: decorator (~=5.1.0)
Requires-Dist: cssselect (>=1.1.0)
Requires-Dist: pyquery (>=1.4.3)
Requires-Dist: future (>=0.18.1)
Requires-Dist: PyHive (>=0.6.3)
Requires-Dist: pyftpdlib (>=1.5.5)
Requires-Dist: pycryptodome (>=3.11.0)
Requires-Dist: nb-http-client
Requires-Dist: clipboard
Requires-Dist: sqlalchemy (~=1.4.49)
Requires-Dist: sqlalchemy-utils (~=0.41.1)
Requires-Dist: biplist
Requires-Dist: fastapi
Requires-Dist: guesstime
Requires-Dist: python-multipart
Requires-Dist: uvicorn
Requires-Dist: curl-cffi
Provides-Extra: oracled
Requires-Dist: cx-Oracle (==7.2.3) ; extra == 'oracled'
Provides-Extra: http
Requires-Dist: http-parser ; extra == 'http'
Provides-Extra: rar
Requires-Dist: unrar-cffi ; extra == 'rar'
